{
    "action": [
        {
            "Title": "The Avengers",
            "Year": "2012",
            "Rated": "PG-13",
            "Released": "04 May 2012",
            "Runtime": "143 min",
            "Genre": "Action, Adventure, Sci-Fi",
            "Director_IDs": [
                "1"
            ],
            "Writer_IDs": [
                "1",
                "2"
            ],
            "Actor_IDs": [
                "3",
                "4",
                "5",
                "5"
            ],
            "Plot": "Earth's mightiest heroes must come together and learn to fight as a team if they are going to stop the mischievous Loki and his alien army from enslaving humanity.",
            "Language": "English, Russian, Hindi",
            "Country": "USA",
            "Awards": "Nominated for 1 Oscar. Another 38 wins & 79 nominations.",
            "Poster": "https://m.media-amazon.com/images/M/MV5BNDYxNjQyMjAtNTdiOS00NGYwLWFmNTAtNThmYjU5ZGI2YTI1XkEyXkFqcGdeQXVyMTMxODk2OTU@._V1_SX300.jpg",
            "Ratings": [
                {
                    "Source": "Internet Movie Database",
                    "Value": "8.0/10"
                },
                {
                    "Source": "Rotten Tomatoes",
                    "Value": "92%"
                },
                {
                    "Source": "Metacritic",
                    "Value": "69/100"
                }
            ],
            "Metascore": "69",
            "imdbRating": "8.0",
            "imdbVotes": "1,242,741",
            "imdbID": "tt0848228",
            "Type": "movie",
            "DVD": "N/A",
            "BoxOffice": "N/A",
            "Production": "Marvel Studios",
            "Website": "N/A",
            "Response": "True"
        },
        {
            "Title": "Avengers: Endgame",
            "Year": "2019",
            "Rated": "PG-13",
            "Released": "26 Apr 2019",
            "Runtime": "181 min",
            "Genre": "Action, Adventure, Drama, Sci-Fi",
            "Director_IDs": [
                "7",
                "8"
            ],
            "Writer_IDs": [
                "9",
                "10"
            ],
            "Actor_IDs": [
                "3",
                "4",
                "5",
                "6"
            ],
            "Plot": "After the devastating events of Avengers: Infinity War (2018), the universe is in ruins. With the help of remaining allies, the Avengers assemble once more in order to reverse Thanos' actions and restore balance to the universe.",
            "Language": "English, Japanese, Xhosa, German",
            "Country": "USA",
            "Awards": "Nominated for 1 Oscar. Another 65 wins & 103 nominations.",
            "Poster": "https://m.media-amazon.com/images/M/MV5BMTc5MDE2ODcwNV5BMl5BanBnXkFtZTgwMzI2NzQ2NzM@._V1_SX300.jpg",
            "Ratings": [
                {
                    "Source": "Internet Movie Database",
                    "Value": "8.4/10"
                },
                {
                    "Source": "Rotten Tomatoes",
                    "Value": "94%"
                },
                {
                    "Source": "Metacritic",
                    "Value": "78/100"
                }
            ],
            "Metascore": "78",
            "imdbRating": "8.4",
            "imdbVotes": "762,149",
            "imdbID": "tt4154796",
            "Type": "movie",
            "DVD": "N/A",
            "BoxOffice": "N/A",
            "Production": "Marvel Studios, Walt Disney Pictures",
            "Website": "N/A",
            "Response": "True"
        },
        {
            "Title": "Captain America: The First Avenger",
            "Year": "2011",
            "Rated": "PG-13",
            "Released": "22 Jul 2011",
            "Runtime": "124 min",
            "Genre": "Action, Adventure, Sci-Fi",
            "Director_IDs": [
                "11"
            ],
            "Writer_IDs": [
                "9",
                "10",
                "12",
                "13"
            ],
            "Actor_IDs": [
                "4",
                "14",
                "15",
                "16"
            ],
            "Plot": "Steve Rogers, a rejected military soldier, transforms into Captain America after taking a dose of a \"Super-Soldier serum\". But being Captain America comes at a price as he attempts to take down a war monger and a terrorist organization.",
            "Language": "English, Norwegian, French",
            "Country": "USA",
            "Awards": "4 wins & 46 nominations.",
            "Poster": "https://m.media-amazon.com/images/M/MV5BMTYzOTc2NzU3N15BMl5BanBnXkFtZTcwNjY3MDE3NQ@@._V1_SX300.jpg",
            "Ratings": [
                {
                    "Source": "Internet Movie Database",
                    "Value": "6.9/10"
                },
                {
                    "Source": "Rotten Tomatoes",
                    "Value": "80%"
                },
                {
                    "Source": "Metacritic",
                    "Value": "66/100"
                }
            ],
            "Metascore": "66",
            "imdbRating": "6.9",
            "imdbVotes": "725,377",
            "imdbID": "tt0458339",
            "Type": "movie",
            "DVD": "N/A",
            "BoxOffice": "N/A",
            "Production": "Marvel Enterprises",
            "Website": "N/A",
            "Response": "True"
        },
        {
            "Title": "The Dark Knight",
            "Year": "2008",
            "Rated": "PG-13",
            "Released": "18 Jul 2008",
            "Runtime": "152 min",
            "Genre": "Action, Crime, Drama, Thriller",
            "Director_IDs": [
                "17"
            ],
            "Writer_IDs": [
                "18",
                "17",
                "19",
                "20"
            ],
            "Actor_IDs": [
                "21",
                "22",
                "23",
                "24"
            ],
            "Plot": "When the menace known as the Joker wreaks havoc and chaos on the people of Gotham, Batman must accept one of the greatest psychological and physical tests of his ability to fight injustice.",
            "Language": "English, Mandarin",
            "Country": "USA, UK",
            "Awards": "Won 2 Oscars. Another 153 wins & 160 nominations.",
            "Poster": "https://m.media-amazon.com/images/M/MV5BMTMxNTMwODM0NF5BMl5BanBnXkFtZTcwODAyMTk2Mw@@._V1_SX300.jpg",
            "Ratings": [
                {
                    "Source": "Internet Movie Database",
                    "Value": "9.0/10"
                },
                {
                    "Source": "Rotten Tomatoes",
                    "Value": "94%"
                },
                {
                    "Source": "Metacritic",
                    "Value": "84/100"
                }
            ],
            "Metascore": "84",
            "imdbRating": "9.0",
            "imdbVotes": "2,245,394",
            "imdbID": "tt0468569",
            "Type": "movie",
            "DVD": "N/A",
            "BoxOffice": "N/A",
            "Production": "Syncopy",
            "Website": "N/A",
            "Response": "True"
        },
        {
            "Title": "Inception",
            "Year": "2010",
            "Rated": "PG-13",
            "Released": "16 Jul 2010",
            "Runtime": "148 min",
            "Genre": "Action, Adventure, Sci-Fi, Thriller",
            "Director_IDs": [
                "17"
            ],
            "Writer_IDs": [
                "17"
            ],
            "Actor_IDs": [
                "25",
                "26",
                "27",
                "28"
            ],
            "Plot": "A thief who steals corporate secrets through the use of dream-sharing technology is given the inverse task of planting an idea into the mind of a C.E.O.",
            "Language": "English, Japanese, French",
            "Country": "USA, UK",
            "Awards": "Won 4 Oscars. Another 152 wins & 217 nominations.",
            "Poster": "https://m.media-amazon.com/images/M/MV5BMjAxMzY3NjcxNF5BMl5BanBnXkFtZTcwNTI5OTM0Mw@@._V1_SX300.jpg",
            "Ratings": [
                {
                    "Source": "Internet Movie Database",
                    "Value": "8.8/10"
                },
                {
                    "Source": "Rotten Tomatoes",
                    "Value": "87%"
                },
                {
                    "Source": "Metacritic",
                    "Value": "74/100"
                }
            ],
            "Metascore": "74",
            "imdbRating": "8.8",
            "imdbVotes": "2,003,841",
            "imdbID": "tt1375666",
            "Type": "movie",
            "DVD": "N/A",
            "BoxOffice": "N/A",
            "Production": "Syncopy, Warner Bros.",
            "Website": "N/A",
            "Response": "True"
        },
        {
            "Title": "The Dark Knight Rises",
            "Year": "2012",
            "Rated": "PG-13",
            "Released": "20 Jul 2012",
            "Runtime": "164 min",
            "Genre": "Action, Adventure",
            "Director_IDs": [
                "17"
            ],
            "Writer_IDs": [
                "18",
                "17",
                "19",
                "20"
            ],
            "Actor_IDs": [
                "21",
                "29",
                "28",
                "26"
            ],
            "Plot": "Eight years after the Joker's reign of anarchy, Batman, with the help of the enigmatic Catwoman, is forced from his exile to save Gotham City from the brutal guerrilla terrorist Bane.",
            "Language": "English, Arabic",
            "Country": "UK, USA",
            "Awards": "Nominated for 1 BAFTA Film Award. Another 38 wins & 101 nominations.",
            "Poster": "https://m.media-amazon.com/images/M/MV5BMTk4ODQzNDY3Ml5BMl5BanBnXkFtZTcwODA0NTM4Nw@@._V1_SX300.jpg",
            "Ratings": [
                {
                    "Source": "Internet Movie Database",
                    "Value": "8.4/10"
                },
                {
                    "Source": "Rotten Tomatoes",
                    "Value": "87%"
                },
                {
                    "Source": "Metacritic",
                    "Value": "78/100"
                }
            ],
            "Metascore": "78",
            "imdbRating": "8.4",
            "imdbVotes": "1,487,503",
            "imdbID": "tt1345836",
            "Type": "movie",
            "DVD": "N/A",
            "BoxOffice": "N/A",
            "Production": "Syncopy",
            "Website": "N/A",
            "Response": "True"
        },
        {
            "Title": "Batman Begins",
            "Year": "2005",
            "Rated": "PG-13",
            "Released": "15 Jun 2005",
            "Runtime": "140 min",
            "Genre": "Action, Adventure",
            "Director_IDs": [
                "17"
            ],
            "Writer_IDs": [
                "20",
                "19",
                "17"
            ],
            "Actor_IDs": [
                "21",
                "24",
                "30",
                "31"
            ],
            "Plot": "After training with his mentor, Batman begins his fight to free crime-ridden Gotham City from corruption.",
            "Language": "English, Mandarin",
            "Country": "USA, UK",
            "Awards": "Nominated for 1 Oscar. Another 14 wins & 72 nominations.",
            "Poster": "https://m.media-amazon.com/images/M/MV5BOTY4YjI2N2MtYmFlMC00ZjcyLTg3YjEtMDQyM2ZjYzQ5YWFkXkEyXkFqcGdeQXVyMTQxNzMzNDI@._V1_SX300.jpg",
            "Ratings": [
                {
                    "Source": "Internet Movie Database",
                    "Value": "8.2/10"
                },
                {
                    "Source": "Rotten Tomatoes",
                    "Value": "84%"
                },
                {
                    "Source": "Metacritic",
                    "Value": "70/100"
                }
            ],
            "Metascore": "70",
            "imdbRating": "8.2",
            "imdbVotes": "1,283,912",
            "imdbID": "tt0372784",
            "Type": "movie",
            "DVD": "N/A",
            "BoxOffice": "N/A",
            "Production": "Warner Brothers, Di Bonaventura Pictures",
            "Website": "N/A",
            "Response": "True"
        }
    ],
    "drama": [
        {
            "Title": "Forrest Gump",
            "Year": "1994",
            "Rated": "PG-13",
            "Released": "06 Jul 1994",
            "Runtime": "142 min",
            "Genre": "Drama, Romance",
            "Director_IDs": [
                "32"
            ],
            "Writer_IDs": [
                "33",
                "34"
            ],
            "Actor_IDs": [
                "35",
                "36",
                "37",
                "38"
            ],
            "Plot": "The presidencies of Kennedy and Johnson, the events of Vietnam, Watergate and other historical events unfold through the perspective of an Alabama man with an IQ of 75, whose only desire is to be reunited with his childhood sweetheart.",
            "Language": "English",
            "Country": "USA",
            "Awards": "Won 6 Oscars. Another 44 wins & 75 nominations.",
            "Poster": "https://m.media-amazon.com/images/M/MV5BNWIwODRlZTUtY2U3ZS00Yzg1LWJhNzYtMmZiYmEyNmU1NjMzXkEyXkFqcGdeQXVyMTQxNzMzNDI@._V1_SX300.jpg",
            "Ratings": [
                {
                    "Source": "Internet Movie Database",
                    "Value": "8.8/10"
                },
                {
                    "Source": "Rotten Tomatoes",
                    "Value": "71%"
                },
                {
                    "Source": "Metacritic",
                    "Value": "82/100"
                }
            ],
            "Metascore": "82",
            "imdbRating": "8.8",
            "imdbVotes": "1,763,949",
            "imdbID": "tt0109830",
            "Type": "movie",
            "DVD": "N/A",
            "BoxOffice": "N/A",
            "Production": "Paramount Pictures",
            "Website": "N/A",
            "Response": "True"
        },
        {
            "Title": "The Green Mile",
            "Year": "1999",
            "Rated": "R",
            "Released": "10 Dec 1999",
            "Runtime": "189 min",
            "Genre": "Crime, Drama, Fantasy, Mystery",
            "Director_IDs": [
                "39"
            ],
            "Writer_IDs": [
                "40",
                "39"
            ],
            "Actor_IDs": [
                "35",
                "41",
                "42",
                "43"
            ],
            "Plot": "The lives of guards on Death Row are affected by one of their charges: a black man accused of child murder and rape, yet who has a mysterious gift.",
            "Language": "English, French",
            "Country": "USA",
            "Awards": "Nominated for 4 Oscars. Another 15 wins & 33 nominations.",
            "Poster": "https://m.media-amazon.com/images/M/MV5BMTUxMzQyNjA5MF5BMl5BanBnXkFtZTYwOTU2NTY3._V1_SX300.jpg",
            "Ratings": [
                {
                    "Source": "Internet Movie Database",
                    "Value": "8.6/10"
                },
                {
                    "Source": "Rotten Tomatoes",
                    "Value": "78%"
                },
                {
                    "Source": "Metacritic",
                    "Value": "61/100"
                }
            ],
            "Metascore": "61",
            "imdbRating": "8.6",
            "imdbVotes": "1,118,429",
            "imdbID": "tt0120689",
            "Type": "movie",
            "DVD": "N/A",
            "BoxOffice": "N/A",
            "Production": "Warner Brothers, Castle Rock Entertainment, Darkwoods Productions",
            "Website": "N/A",
            "Response": "True"
        },
        {
            "Title": "La La Land",
            "Year": "2016",
            "Rated": "PG-13",
            "Released": "25 Dec 2016",
            "Runtime": "128 min",
            "Genre": "Comedy, Drama, Music, Musical, Romance",
            "Director_IDs": [
                "44"
            ],
            "Writer_IDs": [
                "44"
            ],
            "Actor_IDs": [
                "45",
                "46",
                "47",
                "48"
            ],
            "Plot": "While navigating their careers in Los Angeles, a pianist and an actress fall in love while attempting to reconcile their aspirations for the future.",
            "Language": "English",
            "Country": "USA, Hong Kong",
            "Awards": "Won 6 Oscars. Another 237 wins & 288 nominations.",
            "Poster": "https://m.media-amazon.com/images/M/MV5BMzUzNDM2NzM2MV5BMl5BanBnXkFtZTgwNTM3NTg4OTE@._V1_SX300.jpg",
            "Ratings": [
                {
                    "Source": "Internet Movie Database",
                    "Value": "8.0/10"
                },
                {
                    "Source": "Rotten Tomatoes",
                    "Value": "91%"
                },
                {
                    "Source": "Metacritic",
                    "Value": "94/100"
                }
            ],
            "Metascore": "94",
            "imdbRating": "8.0",
            "imdbVotes": "491,120",
            "imdbID": "tt3783958",
            "Type": "movie",
            "DVD": "N/A",
            "BoxOffice": "N/A",
            "Production": "Summit Entertainment, Marc Platt Productions, Gilbert Films",
            "Website": "N/A",
            "Response": "True"
        }
    ],
    "comedy": [
        {
            "Title": "Knives Out",
            "Year": "2019",
            "Rated": "PG-13",
            "Released": "27 Nov 2019",
            "Runtime": "130 min",
            "Genre": "Comedy, Crime, Drama, Mystery, Thriller",
            "Director_IDs": [
                "49"
            ],
            "Writer_IDs": [
                "49"
            ],
            "Actor_IDs": [
                "50",
                "4",
                "51",
                "52"
            ],
            "Plot": "A detective investigates the death of a patriarch of an eccentric, combative family.",
            "Language": "English, Spanish, Hindi",
            "Country": "USA",
            "Awards": "Nominated for 1 Oscar. Another 45 wins & 93 nominations.",
            "Poster": "https://m.media-amazon.com/images/M/MV5BMGUwZjliMTAtNzAxZi00MWNiLWE2NzgtZGUxMGQxZjhhNDRiXkEyXkFqcGdeQXVyNjU1NzU3MzE@._V1_SX300.jpg",
            "Ratings": [
                {
                    "Source": "Internet Movie Database",
                    "Value": "7.9/10"
                },
                {
                    "Source": "Rotten Tomatoes",
                    "Value": "97%"
                },
                {
                    "Source": "Metacritic",
                    "Value": "82/100"
                }
            ],
            "Metascore": "82",
            "imdbRating": "7.9",
            "imdbVotes": "382,078",
            "imdbID": "tt8946378",
            "Type": "movie",
            "DVD": "12 Jun 2020",
            "BoxOffice": "N/A",
            "Production": "Lionsgate",
            "Website": "N/A",
            "Response": "True"
        },
        {
            "Title": "The Breakfast Club",
            "Year": "1985",
            "Rated": "R",
            "Released": "15 Feb 1985",
            "Runtime": "97 min",
            "Genre": "Comedy, Drama",
            "Director_IDs": [
                "53"
            ],
            "Writer_IDs": [
                "53"
            ],
            "Actor_IDs": [
                "54",
                "55",
                "56",
                "57"
            ],
            "Plot": "Five high school students meet in Saturday detention and discover how they have a lot more in common than they thought.",
            "Language": "English",
            "Country": "USA",
            "Awards": "3 wins.",
            "Poster": "https://m.media-amazon.com/images/M/MV5BOTM5N2ZmZTMtNjlmOS00YzlkLTk3YjEtNTU1ZmQ5OTdhODZhXkEyXkFqcGdeQXVyMTQxNzMzNDI@._V1_SX300.jpg",
            "Ratings": [
                {
                    "Source": "Internet Movie Database",
                    "Value": "7.9/10"
                },
                {
                    "Source": "Rotten Tomatoes",
                    "Value": "89%"
                },
                {
                    "Source": "Metacritic",
                    "Value": "66/100"
                }
            ],
            "Metascore": "66",
            "imdbRating": "7.9",
            "imdbVotes": "349,040",
            "imdbID": "tt0088847",
            "Type": "movie",
            "DVD": "N/A",
            "BoxOffice": "N/A",
            "Production": "Universal Pictures",
            "Website": "N/A",
            "Response": "True"
        }
    ],
    "thriller": [
        {
            "Title": "Panic Room",
            "Year": "2002",
            "Rated": "R",
            "Released": "29 Mar 2002",
            "Runtime": "112 min",
            "Genre": "Crime, Drama, Thriller",
            "Director_IDs": [
                "58"
            ],
            "Writer_IDs": [
                "59"
            ],
            "Actor_IDs": [
                "60",
                "61",
                "62",
                "63"
            ],
            "Plot": "A divorced woman and her diabetic daughter take refuge in their newly-purchased house's safe room, when three men break-in, searching for a missing fortune.",
            "Language": "English",
            "Country": "USA",
            "Awards": "1 win & 9 nominations.",
            "Poster": "https://m.media-amazon.com/images/M/MV5BNmY4ZGFjYTYtMDNmYi00ZDM4LWFjYTgtNmNlZjBmMzg0MzQ3XkEyXkFqcGdeQXVyNDk3NzU2MTQ@._V1_SX300.jpg",
            "Ratings": [
                {
                    "Source": "Internet Movie Database",
                    "Value": "6.8/10"
                },
                {
                    "Source": "Rotten Tomatoes",
                    "Value": "75%"
                },
                {
                    "Source": "Metacritic",
                    "Value": "65/100"
                }
            ],
            "Metascore": "65",
            "imdbRating": "6.8",
            "imdbVotes": "253,175",
            "imdbID": "tt0258000",
            "Type": "movie",
            "DVD": "N/A",
            "BoxOffice": "N/A",
            "Production": "Columbia Pictures, Hofflund/Polone",
            "Website": "N/A",
            "Response": "True"
        }
    ]
}