[
    { "firstName": "Josh", "lastName": "Whedon", "id": "1" },
    { "firstName": "Zak", "lastName": "Penn", "id": "2" },
    { "firstName": "Robert", "lastName": "Downey Jr", "id": "3" },
    { "firstName": "Chris", "lastName": "Evans", "id": "4" },
    { "firstName": "Mark", "lastName": "Ruffalo", "id": "5" },
    { "firstName": "Chris", "lastName": "Hemsworth", "id": "6" },
    { "firstName": "Anthony", "lastName": "Russo", "id": "7" },
    { "firstName": "Joe", "lastName": "Russo", "id": "8" },
    { "firstName": "Christopher", "lastName": "Markus", "id": "9" },
    { "firstName": "Stephen", "lastName": "McFeely", "id": "10" },
    { "firstName": "Joe", "lastName": "Johnston", "id": "11" },
    { "firstName": "Joe", "lastName": "Simon", "id": "12" },
    { "firstName": "Jack", "lastName": "Kirby", "id": "13" },
    { "firstName": "Hayley", "lastName": "Atwell", "id": "14" },
    { "firstName": "Sebastian", "lastName": "Stan", "id": "15" },
    { "firstName": "Tommy Lee", "lastName": "Jones", "id": "16" },
    { "firstName": "Christopher", "lastName": "Nolan", "id": "17" },
    { "firstName": "Jonathan", "lastName": "Nolan", "id": "18" },
    { "firstName": "David S.", "lastName": "Goyer", "id": "19" },
    { "firstName": "Bob", "lastName": "Kane", "id": "20" },
    { "firstName": "Christian", "lastName": "Bale", "id": "21" },
    { "firstName": "Heath", "lastName": "Ledger", "id": "22" },
    { "firstName": "Aaron", "lastName": "Eckhart", "id": "23" },
    { "firstName": "Michael", "lastName": "Caine", "id": "24" },
    { "firstName": "Leonardo", "lastName": "Dicaprio", "id": "25" },
    { "firstName": "Joseph", "lastName": "Gordon-Levitt", "id": "26" },
    { "firstName": "Ellen", "lastName": "Page", "id": "27" },
    { "firstName": "Tom", "lastName": "Hardy", "id": "28" },        
    { "firstName": "Gary", "lastName": "Oldman", "id": "29" },
    { "firstName": "Liam", "lastName": "Neeson", "id": "30" },
    { "firstName": "Katie", "lastName": "Holmes", "id": "31" },
    { "firstName": "Robert", "lastName": "Zemeckis", "id": "32" },
    { "firstName": "Winston", "lastName": "Groom", "id": "33" },
    { "firstName": "Eric", "lastName": "Roth", "id": "34" },
    { "firstName": "Tom", "lastName": "Hanks", "id": "35" },
    { "firstName": "Rebecca", "lastName": "Williams", "id": "36" },
    { "firstName": "Sally", "lastName": "Fields", "id": "37" },
    { "firstName": "Michael", "lastName": "Conner Humphreys", "id": "38" },
    { "firstName": "Frank", "lastName": "Darbont", "id": "39" },
    { "firstName": "Stephen", "lastName": "King", "id": "40" },
    { "firstName": "David", "lastName": "Morse", "id": "41" },
    { "firstName": "Bonnie", "lastName": "Hunt", "id": "42" },
    { "firstName": "Michael Clarke", "lastName": "Duncan", "id": "43" },
    { "firstName": "Damien", "lastName": "Chazelle", "id": "44" },
    { "firstName": "Ryan", "lastName": "Gosling", "id": "45" },
    { "firstName": "Emma", "lastName": "Stone", "id": "46" },
    { "firstName": "Amiee", "lastName": "Conn", "id": "47" },
    { "firstName": "Terry", "lastName": "Walters", "id": "48" },
    { "firstName": "Rian", "lastName": "Johnson", "id": "49" },
    { "firstName": "Daniel", "lastName": "Craig", "id": "50" },
    { "firstName": "Ana", "lastName": "de Armas", "id": "51" },
    { "firstName": "Jamie Lee", "lastName": "Curtis", "id": "52" },
    { "firstName": "John", "lastName": "Hughes", "id": "53" },
    { "firstName": "Emilio", "lastName": "Estevez", "id": "54" },
    { "firstName": "Paul", "lastName": "Gleason", "id": "55" },
    { "firstName": "Anthony Michael", "lastName": "Hall", "id": "56" },
    { "firstName": "John", "lastName": "Kapelos", "id": "57" },
    { "firstName": "David", "lastName": "Fincher", "id": "58" },
    { "firstName": "David", "lastName": "Koepp", "id": "59" },
    { "firstName": "Jodie", "lastName": "Foster", "id": "60" },
    { "firstName": "Kristen", "lastName": "Stewart", "id": "61" },
    { "firstName": "Forest", "lastName": "Whitaker", "id": "62" },
    { "firstName": "Dwight", "lastName": "Yoakam", "id": "63" }
]